{
  "fallback": "minecraft:empty",
  "elements": [
    {
      "element": {
        "element_type": "minecraft:single_pool_element",
        "location": "darkestsouls:ancient_ruin/ancient_ruin1",
        "processors": "minecraft:empty",
        "projection": "rigid"
      },
      "weight": 5
    },
    {
      "element": {
        "element_type": "minecraft:single_pool_element",
        "location": "darkestsouls:ancient_ruin/ancient_ruin2",
        "processors": "minecraft:empty",
        "projection": "rigid"
      },
      "weight": 5
    },
    {
      "element": {
        "element_type": "minecraft:single_pool_element",
        "location": "darkestsouls:ancient_ruin/ancient_ruin3",
        "processors": "minecraft:empty",
        "projection": "rigid"
      },
      "weight": 5
    },
    {
      "element": {
        "element_type": "minecraft:single_pool_element",
        "location": "darkestsouls:ancient_ruin/ancient_ruin4",
        "processors": "minecraft:empty",
        "projection": "rigid"
      },
      "weight": 5
    },
    {
      "element": {
        "element_type": "minecraft:single_pool_element",
        "location": "darkestsouls:ancient_ruin/ancient_ruin5",
        "processors": "minecraft:empty",
        "projection": "rigid"
      },
      "weight": 2
    },
    {
      "element": {
        "element_type": "minecraft:single_pool_element",
        "location": "darkestsouls:ancient_ruin/ancient_ruin6",
        "processors": "minecraft:empty",
        "projection": "rigid"
      },
      "weight": 5
    },
    {
      "element": {
        "element_type": "minecraft:single_pool_element",
        "location": "darkestsouls:ancient_ruin/ancient_ruin7",
        "processors": "minecraft:empty",
        "projection": "rigid"
      },
      "weight": 5
    },
    {
      "element": {
        "element_type": "minecraft:single_pool_element",
        "location": "darkestsouls:ancient_ruin/ancient_ruin8",
        "processors": "minecraft:empty",
        "projection": "rigid"
      },
      "weight": 5
    },
    {
      "element": {
        "element_type": "minecraft:single_pool_element",
        "location": "darkestsouls:ancient_ruin/ancient_ruin9",
        "processors": "minecraft:empty",
        "projection": "rigid"
      },
      "weight": 5
    }
  ]
}